<?xml version="1.0"?>
<ArrayOfDroneCharge xmlns:xsi="http://www.w3.org/2001/XMLSchema-instance" xmlns:xsd="http://www.w3.org/2001/XMLSchema">
  <DroneCharge>
    <DroneId>2</DroneId>
    <StationId>7</StationId>
    <StartTime>2022-02-18T07:54:32.3496139+02:00</StartTime>
  </DroneCharge>
  <DroneCharge>
    <DroneId>3</DroneId>
    <StationId>9</StationId>
    <StartTime>2022-02-18T07:54:45.2903662+02:00</StartTime>
  </DroneCharge>
  <DroneCharge>
    <DroneId>4</DroneId>
    <StationId>2</StationId>
    <StartTime>2022-02-18T07:54:57.6451106+02:00</StartTime>
  </DroneCharge>
  <DroneCharge>
    <DroneId>5</DroneId>
    <StationId>8</StationId>
    <StartTime>2022-02-18T07:55:09.7532389+02:00</StartTime>
  </DroneCharge>
  <DroneCharge>
    <DroneId>6</DroneId>
    <StationId>3</StationId>
    <StartTime>2022-02-18T07:55:23.312221+02:00</StartTime>
  </DroneCharge>
  <DroneCharge>
    <DroneId>7</DroneId>
    <StationId>5</StationId>
    <StartTime>2022-02-18T07:55:33.9958404+02:00</StartTime>
  </DroneCharge>
  <DroneCharge>
    <DroneId>8</DroneId>
    <StationId>7</StationId>
    <StartTime>2022-02-18T07:55:45.105795+02:00</StartTime>
  </DroneCharge>
  <DroneCharge>
    <DroneId>9</DroneId>
    <StationId>9</StationId>
    <StartTime>2022-02-18T07:56:41.7920029+02:00</StartTime>
  </DroneCharge>
  <DroneCharge>
    <DroneId>10</DroneId>
    <StationId>6</StationId>
    <StartTime>2022-02-18T07:56:56.0206907+02:00</StartTime>
  </DroneCharge>
  <DroneCharge>
    <DroneId>11</DroneId>
    <StationId>1</StationId>
    <StartTime>2022-02-18T07:57:14.5020016+02:00</StartTime>
  </DroneCharge>
  <DroneCharge>
    <DroneId>1</DroneId>
    <StationId>3</StationId>
    <StartTime>2022-02-18T08:16:12.3079715+02:00</StartTime>
  </DroneCharge>
  <DroneCharge>
    <DroneId>2</DroneId>
    <StationId>2</StationId>
    <StartTime>2022-02-18T08:16:12.3363232+02:00</StartTime>
  </DroneCharge>
  <DroneCharge>
    <DroneId>3</DroneId>
    <StationId>6</StationId>
    <StartTime>2022-02-18T08:16:12.3587216+02:00</StartTime>
  </DroneCharge>
  <DroneCharge>
    <DroneId>7</DroneId>
    <StationId>6</StationId>
    <StartTime>2022-02-18T08:16:12.4432399+02:00</StartTime>
  </DroneCharge>
  <DroneCharge>
    <DroneId>8</DroneId>
    <StationId>5</StationId>
    <StartTime>2022-02-18T08:16:12.4668837+02:00</StartTime>
  </DroneCharge>
  <DroneCharge>
    <DroneId>9</DroneId>
    <StationId>2</StationId>
    <StartTime>2022-02-18T08:16:12.4875478+02:00</StartTime>
  </DroneCharge>
  <DroneCharge>
    <DroneId>1</DroneId>
    <StationId>2</StationId>
    <StartTime>2022-02-18T09:46:15.8425317+02:00</StartTime>
  </DroneCharge>
  <DroneCharge>
    <DroneId>3</DroneId>
    <StationId>9</StationId>
    <StartTime>2022-02-18T09:46:15.9907845+02:00</StartTime>
  </DroneCharge>
  <DroneCharge>
    <DroneId>4</DroneId>
    <StationId>9</StationId>
    <StartTime>2022-02-18T09:46:16.0448576+02:00</StartTime>
  </DroneCharge>
  <DroneCharge>
    <DroneId>8</DroneId>
    <StationId>5</StationId>
    <StartTime>2022-02-18T09:46:16.2163812+02:00</StartTime>
  </DroneCharge>
  <DroneCharge>
    <DroneId>10</DroneId>
    <StationId>9</StationId>
    <StartTime>2022-02-18T09:46:16.3038272+02:00</StartTime>
  </DroneCharge>
  <DroneCharge>
    <DroneId>2</DroneId>
    <StationId>2</StationId>
    <StartTime>2022-02-18T09:47:00.1137233+02:00</StartTime>
  </DroneCharge>
  <DroneCharge>
    <DroneId>1</DroneId>
    <StationId>5</StationId>
    <StartTime>2022-02-18T09:51:05.8564337+02:00</StartTime>
  </DroneCharge>
  <DroneCharge>
    <DroneId>2</DroneId>
    <StationId>3</StationId>
    <StartTime>2022-02-18T09:51:05.9040692+02:00</StartTime>
  </DroneCharge>
  <DroneCharge>
    <DroneId>4</DroneId>
    <StationId>2</StationId>
    <StartTime>2022-02-18T09:51:05.9866237+02:00</StartTime>
  </DroneCharge>
  <DroneCharge>
    <DroneId>5</DroneId>
    <StationId>5</StationId>
    <StartTime>2022-02-18T09:51:06.0338278+02:00</StartTime>
  </DroneCharge>
  <DroneCharge>
    <DroneId>6</DroneId>
    <StationId>5</StationId>
    <StartTime>2022-02-18T09:51:06.0704728+02:00</StartTime>
  </DroneCharge>
  <DroneCharge>
    <DroneId>9</DroneId>
    <StationId>9</StationId>
    <StartTime>2022-02-18T09:51:06.1651098+02:00</StartTime>
  </DroneCharge>
  <DroneCharge>
    <DroneId>11</DroneId>
    <StationId>5</StationId>
    <StartTime>2022-02-18T09:51:06.2393223+02:00</StartTime>
  </DroneCharge>
  <DroneCharge>
    <DroneId>2</DroneId>
    <StationId>1</StationId>
    <StartTime>2022-02-18T09:55:48.7874987+02:00</StartTime>
  </DroneCharge>
  <DroneCharge>
    <DroneId>3</DroneId>
    <StationId>2</StationId>
    <StartTime>2022-02-18T09:55:48.8313524+02:00</StartTime>
  </DroneCharge>
  <DroneCharge>
    <DroneId>6</DroneId>
    <StationId>1</StationId>
    <StartTime>2022-02-18T09:55:48.9341037+02:00</StartTime>
  </DroneCharge>
  <DroneCharge>
    <DroneId>9</DroneId>
    <StationId>2</StationId>
    <StartTime>2022-02-18T09:55:49.0527179+02:00</StartTime>
  </DroneCharge>
  <DroneCharge>
    <DroneId>10</DroneId>
    <StationId>5</StationId>
    <StartTime>2022-02-18T09:55:49.0909543+02:00</StartTime>
  </DroneCharge>
  <DroneCharge>
    <DroneId>11</DroneId>
    <StationId>5</StationId>
    <StartTime>2022-02-18T09:55:49.1360812+02:00</StartTime>
  </DroneCharge>
  <DroneCharge>
    <DroneId>1</DroneId>
    <StationId>3</StationId>
    <StartTime>2022-02-18T09:56:20.7433809+02:00</StartTime>
  </DroneCharge>
  <DroneCharge>
    <DroneId>3</DroneId>
    <StationId>5</StationId>
    <StartTime>2022-02-18T09:59:57.2670426+02:00</StartTime>
  </DroneCharge>
  <DroneCharge>
    <DroneId>4</DroneId>
    <StationId>2</StationId>
    <StartTime>2022-02-18T09:59:57.3478376+02:00</StartTime>
  </DroneCharge>
  <DroneCharge>
    <DroneId>5</DroneId>
    <StationId>9</StationId>
    <StartTime>2022-02-18T09:59:57.4348692+02:00</StartTime>
  </DroneCharge>
  <DroneCharge>
    <DroneId>7</DroneId>
    <StationId>2</StationId>
    <StartTime>2022-02-18T09:59:57.5674303+02:00</StartTime>
  </DroneCharge>
  <DroneCharge>
    <DroneId>10</DroneId>
    <StationId>5</StationId>
    <StartTime>2022-02-18T09:59:57.7234671+02:00</StartTime>
  </DroneCharge>
  <DroneCharge>
    <DroneId>11</DroneId>
    <StationId>5</StationId>
    <StartTime>2022-02-18T09:59:57.7904234+02:00</StartTime>
  </DroneCharge>
  <DroneCharge>
    <DroneId>1</DroneId>
    <StationId>6</StationId>
    <StartTime>2022-02-18T10:00:21.4948607+02:00</StartTime>
  </DroneCharge>
  <DroneCharge>
    <DroneId>7</DroneId>
    <StationId>4</StationId>
    <StartTime>2022-02-18T10:01:16.8614837+02:00</StartTime>
  </DroneCharge>
  <DroneCharge>
    <DroneId>9</DroneId>
    <StationId>6</StationId>
    <StartTime>2022-02-18T10:01:16.9289255+02:00</StartTime>
  </DroneCharge>
  <DroneCharge>
    <DroneId>10</DroneId>
    <StationId>4</StationId>
    <StartTime>2022-02-18T10:01:16.9754859+02:00</StartTime>
  </DroneCharge>
  <DroneCharge>
    <DroneId>1</DroneId>
    <StationId>3</StationId>
    <StartTime>2022-02-18T10:02:25.425385+02:00</StartTime>
  </DroneCharge>
  <DroneCharge>
    <DroneId>2</DroneId>
    <StationId>1</StationId>
    <StartTime>2022-02-18T10:04:43.1565258+02:00</StartTime>
  </DroneCharge>
  <DroneCharge>
    <DroneId>5</DroneId>
    <StationId>4</StationId>
    <StartTime>2022-02-18T10:04:43.3584934+02:00</StartTime>
  </DroneCharge>
  <DroneCharge>
    <DroneId>7</DroneId>
    <StationId>1</StationId>
    <StartTime>2022-02-18T10:04:43.4632487+02:00</StartTime>
  </DroneCharge>
  <DroneCharge>
    <DroneId>10</DroneId>
    <StationId>4</StationId>
    <StartTime>2022-02-18T10:04:43.6250339+02:00</StartTime>
  </DroneCharge>
  <DroneCharge>
    <DroneId>11</DroneId>
    <StationId>5</StationId>
    <StartTime>2022-02-18T10:04:43.6676431+02:00</StartTime>
  </DroneCharge>
  <DroneCharge>
    <DroneId>3</DroneId>
    <StationId>6</StationId>
    <StartTime>2022-02-18T10:07:10.7368406+02:00</StartTime>
  </DroneCharge>
  <DroneCharge>
    <DroneId>4</DroneId>
    <StationId>6</StationId>
    <StartTime>2022-02-18T10:07:10.9776303+02:00</StartTime>
  </DroneCharge>
  <DroneCharge>
    <DroneId>5</DroneId>
    <StationId>2</StationId>
    <StartTime>2022-02-18T10:07:11.0279396+02:00</StartTime>
  </DroneCharge>
  <DroneCharge>
    <DroneId>10</DroneId>
    <StationId>6</StationId>
    <StartTime>2022-02-18T10:07:11.2893963+02:00</StartTime>
  </DroneCharge>
  <DroneCharge>
    <DroneId>1</DroneId>
    <StationId>6</StationId>
    <StartTime>2022-02-18T10:07:43.2724929+02:00</StartTime>
  </DroneCharge>
  <DroneCharge>
    <DroneId>3</DroneId>
    <StationId>9</StationId>
    <StartTime>2022-02-18T10:12:51.2105509+02:00</StartTime>
  </DroneCharge>
  <DroneCharge>
    <DroneId>5</DroneId>
    <StationId>9</StationId>
    <StartTime>2022-02-18T10:12:51.3887198+02:00</StartTime>
  </DroneCharge>
  <DroneCharge>
    <DroneId>7</DroneId>
    <StationId>2</StationId>
    <StartTime>2022-02-18T10:12:51.5294532+02:00</StartTime>
  </DroneCharge>
  <DroneCharge>
    <DroneId>10</DroneId>
    <StationId>5</StationId>
    <StartTime>2022-02-18T10:12:51.711241+02:00</StartTime>
  </DroneCharge>
  <DroneCharge>
    <DroneId>11</DroneId>
    <StationId>9</StationId>
    <StartTime>2022-02-18T10:12:51.7994529+02:00</StartTime>
  </DroneCharge>
  <DroneCharge>
    <DroneId>1</DroneId>
    <StationId>3</StationId>
    <StartTime>2022-02-18T10:13:22.3757845+02:00</StartTime>
  </DroneCharge>
</ArrayOfDroneCharge>